cloudbase_agent/__init__.py
cloudbase_agent/_tools_utils.py
cloudbase_agent/adapters/__init__.py
cloudbase_agent/adapters/langchain.py
cloudbase_agent/adapters/llamaindex.py
cloudbase_agent/bash/__init__.py
cloudbase_agent/bash/bash_tool.py
cloudbase_agent/bash/utils.py
cloudbase_agent/bash/bash_operator/__init__.py
cloudbase_agent/bash/bash_operator/base_operator.py
cloudbase_agent/bash/bash_operator/local_operator.py
cloudbase_agent/bash/bash_operator/sandbox_operator.py
cloudbase_agent/code_executors/__init__.py
cloudbase_agent/code_executors/base_code_executor.py
cloudbase_agent/code_executors/built_in_code_executor.py
cloudbase_agent/code_executors/code_executor_context.py
cloudbase_agent/code_executors/unsafe_local_code_executor.py
cloudbase_agent/fs/__init__.py
cloudbase_agent/fs/edit_tool.py
cloudbase_agent/fs/env_utils.py
cloudbase_agent/fs/glob_tool.py
cloudbase_agent/fs/grep_tool.py
cloudbase_agent/fs/ls_tool.py
cloudbase_agent/fs/multiedit_tool.py
cloudbase_agent/fs/read_tool.py
cloudbase_agent/fs/str_replace_editor_tool.py
cloudbase_agent/fs/utils.py
cloudbase_agent/fs/write_tool.py
cloudbase_agent/fs/fs_operator/__init__.py
cloudbase_agent/fs/fs_operator/base_operator.py
cloudbase_agent/fs/fs_operator/in_memory_operator.py
cloudbase_agent/fs/fs_operator/sandbox_operator.py
cloudbase_agent/mcp/__init__.py
cloudbase_agent/mcp/agkit_mcp_server.py
cloudbase_agent/mcp/client_tool.py
cloudbase_agent/mcp/mcp_client_manager.py
cloudbase_agent/mcp/mcp_toolkit.py
cloudbase_agent/mcp/types.py
cloudbase_agent/mcp/utils.py
cloudbase_agent_tools-0.1.11.dist-info/METADATA
cloudbase_agent_tools-0.1.11.dist-info/WHEEL
cloudbase_agent_tools-0.1.11.dist-info/RECORD
